sys_tui/__init__.py
sys_tui/__main__.py
sys_tui/app.py
sys_tui/main.py
sys_tui/py.typed
sys_tui/renderables/.gitkeep
sys_tui/views/.gitkeep
sys_tui/widgets/cpu_widget.py
sys_tui-0.1.0.dist-info/entry_points.txt
sys_tui-0.1.0.dist-info/LICENSE
sys_tui-0.1.0.dist-info/WHEEL
sys_tui-0.1.0.dist-info/METADATA
sys_tui-0.1.0.dist-info/RECORD
